dj_static_blog/__init__.py
dj_static_blog/apps.py
dj_static_blog/migrations/__init__.py
dj_static_blog/models.py
dj_static_blog/queryset.py
dj_static_blog/templates/dj_static_blog/post_detail.html
dj_static_blog/templates/dj_static_blog/post_list.html
dj_static_blog/testapp/__init__.py
dj_static_blog/testapp/apps.py
dj_static_blog/testapp/migrations/__init__.py
dj_static_blog/testapp/models.py
dj_static_blog/testapp/urls.py
dj_static_blog/testapp/views.py
dj_static_blog-0.1.1.dist-info/LICENSE
dj_static_blog-0.1.1.dist-info/METADATA
dj_static_blog-0.1.1.dist-info/WHEEL
dj_static_blog-0.1.1.dist-info/RECORD
